crispat/__init__.py
crispat/beta2.py
crispat/beta3.py
crispat/binomial.py
crispat/gauss.py
crispat/import_data_to_anndata.py
crispat/maximum.py
crispat/neg_binomial.py
crispat/poisson.py
crispat/poisson_gauss.py
crispat/quantiles.py
crispat/ratios.py
crispat/umi_t.py
crispat/utils.py
crispat-0.9.10.dist-info/licenses/LICENSE
crispat-0.9.10.dist-info/METADATA
crispat-0.9.10.dist-info/WHEEL
crispat-0.9.10.dist-info/top_level.txt
crispat-0.9.10.dist-info/RECORD
