Metadata-Version: 2.4
Name: crispat
Version: 0.9.10
Summary: CRISPR guide assignment tool
Home-page: https://github.com/velten-group/crispat/tree/main
Author: Jana M. Braunger
Author-email: "Jana M. Braunger" <jana.braunger@cos.uni-heidelberg.de>
Project-URL: Homepage, https://github.com/velten-group/crispat
Classifier: Programming Language :: Python :: 3
Classifier: License :: OSI Approved :: MIT License
Classifier: Operating System :: OS Independent
Requires-Python: >=3.10
License-File: LICENSE
Requires-Dist: anndata>=0.8.0
Requires-Dist: dask>=2023.6.0
Requires-Dist: distributed>=2023.6.0
Requires-Dist: ipywidgets>=8.1.5
Requires-Dist: matplotlib>=3.7.1
Requires-Dist: numpy>=1.24.3
Requires-Dist: pandas>=1.5.3
Requires-Dist: pyro-ppl>=1.8.6
Requires-Dist: scanpy>=1.9.3
Requires-Dist: scipy>=1.9.3
Requires-Dist: seaborn>=0.12.2
Requires-Dist: setuptools>=70.0.0
Requires-Dist: torch>=2.2.0
Requires-Dist: tqdm>=4.66.3
Dynamic: author
Dynamic: home-page
Dynamic: license-file
Dynamic: requires-python
